cogwright/__init__.py
cogwright/__main__.py
cogwright/__version__.py
cogwright/make.py
cogwright-0.0.1.dist-info/DESCRIPTION.rst
cogwright-0.0.1.dist-info/METADATA
cogwright-0.0.1.dist-info/RECORD
cogwright-0.0.1.dist-info/WHEEL
cogwright-0.0.1.dist-info/entry_points.txt
cogwright-0.0.1.dist-info/metadata.json
cogwright-0.0.1.dist-info/top_level.txt
