Metadata-Version: 2.0
Name: cogwright
Version: 0.0.1
Summary: Make python platform wheels out of an archive containing non-python data. Intended for creating platform-specific packaging of pythonic wrappers around prebuilt binary libraries.
